[
    {
        "tag_name": "4.9.1-1.16.5",
        "draft": false,
        "prerelease": false,
        "assets": [
            {
                "name": "Impact-4.9.1-1.16.5.jar",
                "browser_download_url": "https://github.com/ImpactDevelopment/ImpactReleases/releases/download/4.9.1-1.16.5/Impact-4.9.1-1.16.5.jar"
            },
            {
                "name": "Impact-4.9.1-1.16.5.json",
                "browser_download_url": "https://github.com/ImpactDevelopment/ImpactReleases/releases/download/4.9.1-1.16.5/Impact-4.9.1-1.16.5.json"
            },
            {
                "name": "Impact-4.9.1-1.16.5.json.asc",
                "browser_download_url": "https://github.com/ImpactDevelopment/ImpactReleases/releases/download/4.9.1-1.16.5/Impact-4.9.1-1.16.5.json.asc"
            }
        ]
    },
    {
        "tag_name": "4.9.1-1.15.2",
        "draft": false,
        "prerelease": false,
        "assets": [
            {
                "name": "Impact-4.9.1-1.15.2.jar",
                "browser_download_url": "https://github.com/ImpactDevelopment/ImpactReleases/releases/download/4.9.1-1.15.2/Impact-4.9.1-1.15.2.jar"
            },
            {
                "name": "Impact-4.9.1-1.15.2.json",
                "browser_download_url": "https://github.com/ImpactDevelopment/ImpactReleases/releases/download/4.9.1-1.15.2/Impact-4.9.1-1.15.2.json"
            },
            {
                "name": "Impact-4.9.1-1.15.2.json.asc",
                "browser_download_url": "https://github.com/ImpactDevelopment/ImpactReleases/releases/download/4.9.1-1.15.2/Impact-4.9.1-1.15.2.json.asc"
            }
        ]
    },
    {
        "tag_name": "4.9.1-1.14.4",
        "draft": false,
        "prerelease": false,
        "assets": [
            {
                "name": "Impact-4.9.1-1.14.4.jar",
                "browser_download_url": "https://github.com/ImpactDevelopment/ImpactReleases/releases/download/4.9.1-1.14.4/Impact-4.9.1-1.14.4.jar"
            },
            {
                "name": "Impact-4.9.1-1.14.4.json",
                "browser_download_url": "https://github.com/ImpactDevelopment/ImpactReleases/releases/download/4.9.1-1.14.4/Impact-4.9.1-1.14.4.json"
            },
            {
                "name": "Impact-4.9.1-1.14.4.json.asc",
                "browser_download_url": "https://github.com/ImpactDevelopment/ImpactReleases/releases/download/4.9.1-1.14.4/Impact-4.9.1-1.14.4.json.asc"
            }
        ]
    },
    {
        "tag_name": "4.9.1-1.12.2",
        "draft": false,
        "prerelease": false,
        "assets": [
            {
                "name": "Impact-4.9.1-1.12.2.jar",
                "browser_download_url": "https://github.com/ImpactDevelopment/ImpactReleases/releases/download/4.9.1-1.12.2/Impact-4.9.1-1.12.2.jar"
            },
            {
                "name": "Impact-4.9.1-1.12.2.json",
                "browser_download_url": "https://github.com/ImpactDevelopment/ImpactReleases/releases/download/4.9.1-1.12.2/Impact-4.9.1-1.12.2.json"
            },
            {
                "name": "Impact-4.9.1-1.12.2.json.asc",
                "browser_download_url": "https://github.com/ImpactDevelopment/ImpactReleases/releases/download/4.9.1-1.12.2/Impact-4.9.1-1.12.2.json.asc"
            }
        ]
    },
    {
        "tag_name": "nightly-20201224-1.12.2",
        "draft": false,
        "prerelease": true,
        "assets": [
            {
                "name": "Impact-nightly-20201224-1.12.2.jar",
                "browser_download_url": "https://files.impactclient.net/artifacts/Impact/nightly/nightly-20201224-1.12.2/Impact-nightly-20201224-1.12.2.jar"
            },
            {
                "name": "Impact-nightly-20201224-1.12.2.json",
                "browser_download_url": "https://files.impactclient.net/artifacts/Impact/nightly/nightly-20201224-1.12.2/Impact-nightly-20201224-1.12.2.json"
            }
        ]
    }
]